sgains/__init__.py
sgains/__main__.py
sgains/filesIO.py
sgains/logging.config
sgains/plotter.py
sgains/plotting_utils.py
sgains/processor.py
sgains/solutions.py
sgains-0.1.0.dist-info/LICENSE
sgains-0.1.0.dist-info/METADATA
sgains-0.1.0.dist-info/WHEEL
sgains-0.1.0.dist-info/RECORD
